hatching/__init__.py
hatching/auth.py
hatching/hatching.py
hatching-0.0.1.dist-info/LICENSE
hatching-0.0.1.dist-info/METADATA
hatching-0.0.1.dist-info/WHEEL
hatching-0.0.1.dist-info/top_level.txt
hatching-0.0.1.dist-info/RECORD
