Metadata-Version: 2.1
Name: hatching
Version: 0.0.1
Summary: neuropark dashboard
Home-page: https://github.com/neuropark/hatching
Author: neuropark
Author-email: contact@neuropark.co
License: UNKNOWN
Project-URL: Bug Tracker, https://github.com/neuropark/hatching/issues
Platform: UNKNOWN
Classifier: Programming Language :: Python :: 3
Classifier: License :: OSI Approved :: MIT License
Classifier: Operating System :: OS Independent
Requires-Python: >=3.6
License-File: LICENSE
